fpass/__init__.py
FanPass-0.0.5.dist-info/METADATA
FanPass-0.0.5.dist-info/WHEEL
FanPass-0.0.5.dist-info/top_level.txt
FanPass-0.0.5.dist-info/RECORD
