Metadata-Version: 2.1
Name: FanPass
Version: 0.0.5
Summary: password generator by iFanpS#9347
Home-page: UNKNOWN
Author: iFanpS
Author-email: imezz8424@gmail.com
License: MIT
Keywords: passgen,ifanpspassgen
Platform: UNKNOWN
Classifier: Development Status :: 3 - Alpha
Classifier: Intended Audience :: Developers
Classifier: Topic :: Software Development :: Build Tools
Classifier: License :: OSI Approved :: MIT License
Classifier: Programming Language :: Python :: 3.8
Classifier: Programming Language :: Python :: 3.9
